radynpy/__init__.py
radynpy/cdf/CdfLoader.py
radynpy/cdf/GenRadynCdfHelp.py
radynpy/cdf/RadynFormatHelp.pickle
radynpy/cdf/RadynKeyFile.py
radynpy/cdf/RadynKeySizes.pickle
radynpy/cdf/__init__.py
radynpy/cdf/auxtypes/AuxTypes.py
radynpy/cdf/auxtypes/__init__.py
radynpy/matsplotlib/ContribFn.py
radynpy/matsplotlib/Opacity.py
radynpy/matsplotlib/__init__.py
radynpy/matsplotlib/opctab.dat
radynpy/utils/Utils.py
radynpy/utils/__init__.py
radynpy-0.5.0.dist-info/LICENSE
radynpy-0.5.0.dist-info/METADATA
radynpy-0.5.0.dist-info/WHEEL
radynpy-0.5.0.dist-info/top_level.txt
radynpy-0.5.0.dist-info/zip-safe
radynpy-0.5.0.dist-info/RECORD
