Metadata-Version: 2.1
Name: radynpy
Version: 0.5.0
Summary: Analysis tools for Radyn in Python
Home-page: http://github.com/Goobley/radynpy
Author: Chris Osborne
Author-email: c.osborne.1@research.gla.ac.uk
License: MIT
Platform: UNKNOWN
Classifier: Development Status :: 3 - Alpha
Classifier: Intended Audience :: Science/Research
Classifier: License :: OSI Approved :: MIT License
Requires-Dist: numpy
Requires-Dist: scikit-image
Requires-Dist: matplotlib
Requires-Dist: scipy
Requires-Dist: colour
Requires-Dist: palettable
Requires-Dist: cdflib
